pikaia/__init__.py
pikaia/alg.py
pikaia/examples.py
pikaia/plot.py
pikaia/search.py
pikaia-0.0.3.dist-info/METADATA
pikaia-0.0.3.dist-info/WHEEL
pikaia-0.0.3.dist-info/licenses/LICENSE
pikaia-0.0.3.dist-info/RECORD
