Metadata-Version: 2.3
Name: pikaia
Version: 0.0.3
Summary: Data analysis with evolutionary simulation
Project-URL: Homepage, https://github.com/danube-ai/pikaia
Project-URL: Issues, https://github.com/danube-ai/pikaia/issues
Author-email: Philipp Wissgott <philipp@danube.ai>, Andreas Roschal <andreas@danube.ai>, Martin Bär <martin@danube.ai>
License: MIT
Keywords: AI,data analysis,evolutionary simulation
Classifier: Operating System :: OS Independent
Classifier: Programming Language :: Python :: 3
Requires-Python: >=3.8
Requires-Dist: matplotlib>=3.6.3
Requires-Dist: numpy
Requires-Dist: pandas>=1.5.3
